aiotrello/Trello.py
aiotrello/__init__.py
aiotrello/exceptions.py
aiotrello/misc/__init__.py
aiotrello/misc/constants.py
aiotrello/structures/Board.py
aiotrello/structures/Card.py
aiotrello/structures/List.py
aiotrello/structures/__init__.py
aiotrello/utils/__init__.py
aiotrello/utils/request.py
aiotrello-0.0.7.7.dist-info/LICENSE.txt
aiotrello-0.0.7.7.dist-info/METADATA
aiotrello-0.0.7.7.dist-info/WHEEL
aiotrello-0.0.7.7.dist-info/top_level.txt
aiotrello-0.0.7.7.dist-info/RECORD
