Metadata-Version: 2.1
Name: aiotrello
Version: 0.0.7.7
Summary: Async Trello library
Home-page: https://github.com/zomien/aiotrello
Author: Julien Kmec
Author-email: me@julien.dev
License: MIT
Keywords: async,trello
Platform: UNKNOWN
Classifier: Programming Language :: Python :: 3.5
Classifier: Programming Language :: Python :: 3.6
Classifier: Programming Language :: Python :: 3.7
Classifier: Operating System :: OS Independent
